{
  "iteration_count": 4,
  "farm": {
    "s3_bucket": "dota2bot-batch-results-4924",
    "run_prefixes": [
      "soak/run_20260719_0455",
      "soak/run_20260719_0630",
      "soak/run_20260719_0716"
    ],
    "instance_tag": "dota2bot-soak"
  },
  "watermark": {
    "last_processed_key": "20260719_065127_slot4.analysis.json",
    "games_ingested_total": 41
  },
  "fixed_issues": [
    "side_bias:soak_draft_frozen_radiant_lineup",
    "provenance:script_version_unknown",
    "provenance:farm_dirty_general_lua",
    "slow_close:push_desire_gates",
    "slow_close:no_game_time_cap",
    "mode_detect:courier_speed_heuristic",
    "sniper:shrapnel_charge_api"
  ],
  "open_issues": [
    {
      "key": "outcome_scoring:iter_0004",
      "note": "OWNER ACCEPTANCE CRITERIA (2026-07-19, this stage passes if): (1) first T1 falls at 10-20 game-min (ideal 5-10, tolerated to 20); (2) T2s fall ~30 min; (3) all towers that should fall are down before 40 min. Do NOT hard-block on ideal timing \u2014 bot farm efficiency/micro polish comes later, per-hero. Score iter-0004 from soak/run_20260719_0716 against these. Live so far: T1s 10.7-22.6min (mostly in range), first T2s 24-26min (ahead of the 30min line). Also verify winner meaningful + no feeding-while-ahead.",
      "first_seen_iter": 2
    },
    {
      "key": "push_think:tower_yoyo",
      "note": "PushThink retreats on a single tower hit whenever a creep wave is present (WasRecentlyDamagedByTower window 2-4s) -> bots yo-yo under towers, gutting building DPS. Micro change; verify in-game before touching. aba_push.lua PushThink, TS mirror.",
      "first_seen_iter": 2
    },
    {
      "key": "fight_desire:possibly_low",
      "note": "Owner observation (live watching iter-0004): bots' fight willingness seems weak and push tempo slower than human games \u2014 no proactive 'take tower after won fight' linkage, no dedicated push strategy. Long-term per-hero/macro polish item, not a blocker for this stage.",
      "first_seen_iter": 4
    },
    {
      "key": "vscript_errors:masked",
      "note": "11-20/game 'error in error handling', no consistent context. Bot-VM print() does NOT reach dedicated-server console, so in-game markers are invisible \u2014 unmasking needs an error()-based emit or on-instance probe of a live game.",
      "first_seen_iter": 1
    },
    {
      "key": "loser_building_damage:zero",
      "note": "Pre-fix losing side did ~0 building dmg. If this persists with fair drafts (post iter-0001 cohort), hunt a defend-lock in mode desires beyond the fixed gates.",
      "first_seen_iter": 2
    },
    {
      "key": "script_perf:GetDesire",
      "note": "All games flag GetDesire hotspots, max ~7ms (sniper/CM/lion/PA/slardar...). Frame-budget risk; profile after macro fixes settle.",
      "first_seen_iter": 1
    },
    {
      "key": "invalid_orders:dead_targets",
      "note": "~74/game engine rejections: orders on dead units (order 19/20). Sloppy target validation, low priority.",
      "first_seen_iter": 2
    },
    {
      "key": "feeder:pending_rebaseline",
      "note": "Pre-fix feeder/low_gpm stats (lich 55K/207D etc.) all confounded by rigged draft. Re-rank from post-iter-0002 games.",
      "first_seen_iter": 1
    }
  ],
  "last_release_tag": "v0.1-baseline",
  "next_ab_after_iteration": 5,
  "deploys": {
    "iter-0001": {
      "commit": "e18bd457ccd37eeecdd15616db50a44a5580478d",
      "deployed_utc": "2026-07-19T06:30:00Z",
      "run_prefix_started": "soak/run_20260719_0630",
      "note": "remote tag push blocked by env git proxy; tag exists on farm checkout + locally. Farm loops restarted for version-stamp provenance."
    },
    "iter-0002": {
      "commit": "bd62ec0",
      "deployed_utc": "2026-07-19T06:49:45Z",
      "run_prefix_started": null,
      "note": "same run prefix (soak/run_20260719_0630); no loop restart needed. Cohort split by script_version stamp: iter-0001* = draft fix only, iter-0002* = +push/turbo/sniper fixes."
    },
    "iter-0003": {
      "commit": "81c2eec",
      "deployed_utc": "2026-07-19T07:15:00Z",
      "run_prefix_started": null,
      "note": "overtime forfeit cap (40 game-min). Also restored stale general.lua on farm \u2014 stamps before this read 'iter-0001-dirty' etc.; clean from here."
    },
    "iter-0004": {
      "commit": "9260ccf",
      "deployed_utc": "2026-07-19T07:16:00Z",
      "run_prefix_started": "soak/run_20260719_0716",
      "note": "push caps 0.85/0.95 + closing urgency (turbo>25min). Farm fully restarted on iter-0004 per owner; in-flight iter-0002/0003 games sacrificed. 35-min wall backstop + 40-min overtime forfeit both active. Score from run_20260719_0716: first-rax <28min, most games 25-35min."
    }
  }
}